pyfps/__init__.py
pyfps-1.0.5.dist-info/LICENSE
pyfps-1.0.5.dist-info/METADATA
pyfps-1.0.5.dist-info/WHEEL
pyfps-1.0.5.dist-info/top_level.txt
pyfps-1.0.5.dist-info/RECORD
