Metadata-Version: 2.1
Name: pyfps
Version: 1.0.5
Summary: python fps tool
Home-page: https://github.com/bjtj/python-fps
Author: bjtj
Author-email: bjtj10@gmail.com
Classifier: Programming Language :: Python :: 3
Classifier: License :: OSI Approved :: MIT License
Classifier: Operating System :: OS Independent
License-File: LICENSE
